[
    {
        "link": "https://sites.icmc.usp.br/szani/alglin.pdf",
        "title": "Álgebra Linear - Sergio Luis Zani"
    },
    {
        "link": "http://www.mat.ufpb.br/jorge/arquivos/disciplinas/listas/LivroIAL",
        "title": "Introdução a Àlgebra Linear - Antônio de Andrade"
    },
    {
        "link": "https://mtmgrad.paginas.ufsc.br/files/2014/04/%C3%81lgebra-Linear-I.pdf",
        "title": "Álgebra Linear - Sonia/Daniel"
    },
    
    {
        "link": "https://drive.google.com/file/d/1skVvhrYdjg5ts8nbKvShVayuSk2yvp9n/view?usp=sharing",
        "title": "Sistemas operacionais - Conceitos e Mecanismos",
        "description": "Livro sobre teoria no desenvolvimento de sistemas operacionais.",
        "author": "Carlos A. Maziero"
    }
]
